hydra_callbacks/__init__.py
hydra_callbacks/_version.py
hydra_callbacks/callbacks.py
hydra_callbacks/logger.py
hydra_callbacks/monitor.py
hydra_callbacks-0.6.1.dist-info/LICENSE
hydra_callbacks-0.6.1.dist-info/METADATA
hydra_callbacks-0.6.1.dist-info/WHEEL
hydra_callbacks-0.6.1.dist-info/top_level.txt
hydra_callbacks-0.6.1.dist-info/RECORD
