Metadata-Version: 2.1
Name: hydra-callbacks
Version: 0.6.1
Summary: A collection of usefull hydra callbacks for hydra configuration
Author-email: Pierre-Antoine Comby <pierre-antoine.comby@cea.fr>
Project-URL: Homepage, https://github.com/paquiteau/hydra-callbacks
Project-URL: Bug Reports, https://github.com/paquiteau/hydra-callbacks/issues
Project-URL: Sources, https://github.com/paquiteau/hydra-callbacks
Keywords: hydra,configuration,callback
Classifier: Development Status :: 3 - Alpha
Classifier: Intended Audience :: Developers
Classifier: License :: OSI Approved :: MIT License
Classifier: Programming Language :: Python :: 3.9
Classifier: Programming Language :: Python :: 3.10
Classifier: Programming Language :: Python :: 3.11
Requires-Python: >=3.8
License-File: LICENSE
Requires-Dist: hydra-core
Requires-Dist: GitPython
Requires-Dist: pandas
Requires-Dist: numpy
Requires-Dist: fastparquet
Requires-Dist: psutil
Provides-Extra: dev
Requires-Dist: black ; extra == 'dev'
Requires-Dist: isort ; extra == 'dev'
Requires-Dist: ruff ; extra == 'dev'
Provides-Extra: test
Requires-Dist: pytest ; extra == 'test'
Requires-Dist: pytest-cov ; extra == 'test'
Requires-Dist: pytest-xdist ; extra == 'test'
Requires-Dist: pytest-sugar ; extra == 'test'
